[{"CanFly":true,"Id":0,"Name":"Essence 0"},{"CanFly":false,"Id":1,"Name":"Essence 1"},{"CanFly":true,"Id":2,"Name":"Essence 2"},{"CanFly":false,"Id":3,"Name":"Essence 3"},{"CanFly":true,"Id":4,"Name":"Essence 4"},{"CanFly":false,"Id":5,"Name":"Essence 5"},{"CanFly":true,"Id":6,"Name":"Essence 6"},{"CanFly":false,"Id":7,"Name":"Essence 7"},{"CanFly":true,"Id":8,"Name":"Essence 8"},{"CanFly":false,"Id":9,"Name":"Essence 9"},{"CanFly":true,"Id":10,"Name":"Essence 10"},{"CanFly":false,"Id":11,"Name":"Essence 11"},{"CanFly":true,"Id":12,"Name":"Essence 12"},{"CanFly":false,"Id":13,"Name":"Essence 13"},{"CanFly":true,"Id":14,"Name":"Essence 14"},{"CanFly":false,"Id":15,"Name":"Essence 15"},{"CanFly":true,"Id":16,"Name":"Essence 16"},{"CanFly":false,"Id":17,"Name":"Essence 17"},{"CanFly":true,"Id":18,"Name":"Essence 18"},{"CanFly":false,"Id":19,"Name":"Essence 19"},{"CanFly":true,"Id":20,"Name":"Essence 20"},{"CanFly":false,"Id":21,"Name":"Essence 21"},{"CanFly":true,"Id":22,"Name":"Essence 22"},{"CanFly":false,"Id":23,"Name":"Essence 23"},{"CanFly":true,"Id":24,"Name":"Essence 24"},{"CanFly":false,"Id":25,"Name":"Essence 25"},{"CanFly":true,"Id":26,"Name":"Essence 26"},{"CanFly":false,"Id":27,"Name":"Essence 27"},{"CanFly":true,"Id":28,"Name":"Essence 28"},{"CanFly":false,"Id":29,"Name":"Essence 29"},{"CanFly":true,"Id":30,"Name":"Essence 30"},{"CanFly":false,"Id":31,"Name":"Essence 31"},{"CanFly":true,"Id":32,"Name":"Essence 32"},{"CanFly":false,"Id":33,"Name":"Essence 33"},{"CanFly":true,"Id":34,"Name":"Essence 34"},{"CanFly":false,"Id":35,"Name":"Essence 35"},{"CanFly":true,"Id":36,"Name":"Essence 36"},{"CanFly":false,"Id":37,"Name":"Essence 37"},{"CanFly":true,"Id":38,"Name":"Essence 38"},{"CanFly":false,"Id":39,"Name":"Essence 39"},{"CanFly":true,"Id":40,"Name":"Essence 40"},{"CanFly":false,"Id":41,"Name":"Essence 41"},{"CanFly":true,"Id":42,"Name":"Essence 42"},{"CanFly":false,"Id":43,"Name":"Essence 43"},{"CanFly":true,"Id":44,"Name":"Essence 44"},{"CanFly":false,"Id":45,"Name":"Essence 45"},{"CanFly":true,"Id":46,"Name":"Essence 46"},{"CanFly":false,"Id":47,"Name":"Essence 47"},{"CanFly":true,"Id":48,"Name":"Essence 48"},{"CanFly":false,"Id":49,"Name":"Essence 49"},{"CanFly":true,"Id":50,"Name":"Essence 50"},{"CanFly":false,"Id":51,"Name":"Essence 51"},{"CanFly":true,"Id":52,"Name":"Essence 52"},{"CanFly":false,"Id":53,"Name":"Essence 53"},{"CanFly":true,"Id":54,"Name":"Essence 54"},{"CanFly":false,"Id":55,"Name":"Essence 55"},{"CanFly":true,"Id":56,"Name":"Essence 56"},{"CanFly":false,"Id":57,"Name":"Essence 57"},{"CanFly":true,"Id":58,"Name":"Essence 58"},{"CanFly":false,"Id":59,"Name":"Essence 59"},{"CanFly":true,"Id":60,"Name":"Essence 60"},{"CanFly":false,"Id":61,"Name":"Essence 61"},{"CanFly":true,"Id":62,"Name":"Essence 62"},{"CanFly":false,"Id":63,"Name":"Essence 63"},{"CanFly":true,"Id":64,"Name":"Essence 64"},{"CanFly":false,"Id":65,"Name":"Essence 65"},{"CanFly":true,"Id":66,"Name":"Essence 66"},{"CanFly":false,"Id":67,"Name":"Essence 67"},{"CanFly":true,"Id":68,"Name":"Essence 68"},{"CanFly":false,"Id":69,"Name":"Essence 69"},{"CanFly":true,"Id":70,"Name":"Essence 70"},{"CanFly":false,"Id":71,"Name":"Essence 71"},{"CanFly":true,"Id":72,"Name":"Essence 72"},{"CanFly":false,"Id":73,"Name":"Essence 73"},{"CanFly":true,"Id":74,"Name":"Essence 74"},{"CanFly":false,"Id":75,"Name":"Essence 75"},{"CanFly":true,"Id":76,"Name":"Essence 76"},{"CanFly":false,"Id":77,"Name":"Essence 77"},{"CanFly":true,"Id":78,"Name":"Essence 78"},{"CanFly":false,"Id":79,"Name":"Essence 79"},{"CanFly":true,"Id":80,"Name":"Essence 80"},{"CanFly":false,"Id":81,"Name":"Essence 81"},{"CanFly":true,"Id":82,"Name":"Essence 82"},{"CanFly":false,"Id":83,"Name":"Essence 83"},{"CanFly":true,"Id":84,"Name":"Essence 84"},{"CanFly":false,"Id":85,"Name":"Essence 85"},{"CanFly":true,"Id":86,"Name":"Essence 86"},{"CanFly":false,"Id":87,"Name":"Essence 87"},{"CanFly":true,"Id":88,"Name":"Essence 88"},{"CanFly":false,"Id":89,"Name":"Essence 89"},{"CanFly":true,"Id":90,"Name":"Essence 90"},{"CanFly":false,"Id":91,"Name":"Essence 91"},{"CanFly":true,"Id":92,"Name":"Essence 92"},{"CanFly":false,"Id":93,"Name":"Essence 93"},{"CanFly":true,"Id":94,"Name":"Essence 94"},{"CanFly":false,"Id":95,"Name":"Essence 95"},{"CanFly":true,"Id":96,"Name":"Essence 96"},{"CanFly":false,"Id":97,"Name":"Essence 97"},{"CanFly":true,"Id":98,"Name":"Essence 98"},{"CanFly":false,"Id":99,"Name":"Essence 99"},{"CanFly":true,"Id":100,"Name":"Essence 100"},{"CanFly":false,"Id":101,"Name":"Essence 101"},{"CanFly":true,"Id":102,"Name":"Essence 102"},{"CanFly":false,"Id":103,"Name":"Essence 103"},{"CanFly":true,"Id":104,"Name":"Essence 104"},{"CanFly":false,"Id":105,"Name":"Essence 105"},{"CanFly":true,"Id":106,"Name":"Essence 106"},{"CanFly":false,"Id":107,"Name":"Essence 107"},{"CanFly":true,"Id":108,"Name":"Essence 108"},{"CanFly":false,"Id":109,"Name":"Essence 109"},{"CanFly":true,"Id":110,"Name":"Essence 110"},{"CanFly":false,"Id":111,"Name":"Essence 111"},{"CanFly":true,"Id":112,"Name":"Essence 112"},{"CanFly":false,"Id":113,"Name":"Essence 113"},{"CanFly":true,"Id":114,"Name":"Essence 114"},{"CanFly":false,"Id":115,"Name":"Essence 115"},{"CanFly":true,"Id":116,"Name":"Essence 116"},{"CanFly":false,"Id":117,"Name":"Essence 117"},{"CanFly":true,"Id":118,"Name":"Essence 118"},{"CanFly":false,"Id":119,"Name":"Essence 119"},{"CanFly":true,"Id":120,"Name":"Essence 120"},{"CanFly":false,"Id":121,"Name":"Essence 121"},{"CanFly":true,"Id":122,"Name":"Essence 122"},{"CanFly":false,"Id":123,"Name":"Essence 123"},{"CanFly":true,"Id":124,"Name":"Essence 124"},{"CanFly":false,"Id":125,"Name":"Essence 125"},{"CanFly":true,"Id":126,"Name":"Essence 126"},{"CanFly":false,"Id":127,"Name":"Essence 127"},{"CanFly":true,"Id":128,"Name":"Essence 128"},{"CanFly":false,"Id":129,"Name":"Essence 129"},{"CanFly":true,"Id":130,"Name":"Essence 130"},{"CanFly":false,"Id":131,"Name":"Essence 131"},{"CanFly":true,"Id":132,"Name":"Essence 132"},{"CanFly":false,"Id":133,"Name":"Essence 133"},{"CanFly":true,"Id":134,"Name":"Essence 134"},{"CanFly":false,"Id":135,"Name":"Essence 135"},{"CanFly":true,"Id":136,"Name":"Essence 136"},{"CanFly":false,"Id":137,"Name":"Essence 137"},{"CanFly":true,"Id":138,"Name":"Essence 138"},{"CanFly":false,"Id":139,"Name":"Essence 139"},{"CanFly":true,"Id":140,"Name":"Essence 140"},{"CanFly":false,"Id":141,"Name":"Essence 141"},{"CanFly":true,"Id":142,"Name":"Essence 142"},{"CanFly":false,"Id":143,"Name":"Essence 143"},{"CanFly":true,"Id":144,"Name":"Essence 144"},{"CanFly":false,"Id":145,"Name":"Essence 145"},{"CanFly":true,"Id":146,"Name":"Essence 146"},{"CanFly":false,"Id":147,"Name":"Essence 147"},{"CanFly":true,"Id":148,"Name":"Essence 148"},{"CanFly":false,"Id":149,"Name":"Essence 149"},{"CanFly":true,"Id":150,"Name":"Essence 150"},{"CanFly":false,"Id":151,"Name":"Essence 151"},{"CanFly":true,"Id":152,"Name":"Essence 152"},{"CanFly":false,"Id":153,"Name":"Essence 153"},{"CanFly":true,"Id":154,"Name":"Essence 154"},{"CanFly":false,"Id":155,"Name":"Essence 155"},{"CanFly":true,"Id":156,"Name":"Essence 156"},{"CanFly":false,"Id":157,"Name":"Essence 157"},{"CanFly":true,"Id":158,"Name":"Essence 158"},{"CanFly":false,"Id":159,"Name":"Essence 159"},{"CanFly":true,"Id":160,"Name":"Essence 160"},{"CanFly":false,"Id":161,"Name":"Essence 161"},{"CanFly":true,"Id":162,"Name":"Essence 162"},{"CanFly":false,"Id":163,"Name":"Essence 163"},{"CanFly":true,"Id":164,"Name":"Essence 164"},{"CanFly":false,"Id":165,"Name":"Essence 165"},{"CanFly":true,"Id":166,"Name":"Essence 166"},{"CanFly":false,"Id":167,"Name":"Essence 167"},{"CanFly":true,"Id":168,"Name":"Essence 168"},{"CanFly":false,"Id":169,"Name":"Essence 169"},{"CanFly":true,"Id":170,"Name":"Essence 170"},{"CanFly":false,"Id":171,"Name":"Essence 171"},{"CanFly":true,"Id":172,"Name":"Essence 172"},{"CanFly":false,"Id":173,"Name":"Essence 173"},{"CanFly":true,"Id":174,"Name":"Essence 174"},{"CanFly":false,"Id":175,"Name":"Essence 175"},{"CanFly":true,"Id":176,"Name":"Essence 176"},{"CanFly":false,"Id":177,"Name":"Essence 177"},{"CanFly":true,"Id":178,"Name":"Essence 178"},{"CanFly":false,"Id":179,"Name":"Essence 179"},{"CanFly":true,"Id":180,"Name":"Essence 180"},{"CanFly":false,"Id":181,"Name":"Essence 181"},{"CanFly":true,"Id":182,"Name":"Essence 182"},{"CanFly":false,"Id":183,"Name":"Essence 183"},{"CanFly":true,"Id":184,"Name":"Essence 184"},{"CanFly":false,"Id":185,"Name":"Essence 185"},{"CanFly":true,"Id":186,"Name":"Essence 186"},{"CanFly":false,"Id":187,"Name":"Essence 187"},{"CanFly":true,"Id":188,"Name":"Essence 188"},{"CanFly":false,"Id":189,"Name":"Essence 189"},{"CanFly":true,"Id":190,"Name":"Essence 190"},{"CanFly":false,"Id":191,"Name":"Essence 191"},{"CanFly":true,"Id":192,"Name":"Essence 192"},{"CanFly":false,"Id":193,"Name":"Essence 193"},{"CanFly":true,"Id":194,"Name":"Essence 194"},{"CanFly":false,"Id":195,"Name":"Essence 195"},{"CanFly":true,"Id":196,"Name":"Essence 196"},{"CanFly":false,"Id":197,"Name":"Essence 197"},{"CanFly":true,"Id":198,"Name":"Essence 198"},{"CanFly":false,"Id":199,"Name":"Essence 199"},{"CanFly":true,"Id":200,"Name":"Essence 200"},{"CanFly":false,"Id":201,"Name":"Essence 201"},{"CanFly":true,"Id":202,"Name":"Essence 202"},{"CanFly":false,"Id":203,"Name":"Essence 203"},{"CanFly":true,"Id":204,"Name":"Essence 204"},{"CanFly":false,"Id":205,"Name":"Essence 205"},{"CanFly":true,"Id":206,"Name":"Essence 206"},{"CanFly":false,"Id":207,"Name":"Essence 207"},{"CanFly":true,"Id":208,"Name":"Essence 208"},{"CanFly":false,"Id":209,"Name":"Essence 209"},{"CanFly":true,"Id":210,"Name":"Essence 210"},{"CanFly":false,"Id":211,"Name":"Essence 211"},{"CanFly":true,"Id":212,"Name":"Essence 212"},{"CanFly":false,"Id":213,"Name":"Essence 213"},{"CanFly":true,"Id":214,"Name":"Essence 214"},{"CanFly":false,"Id":215,"Name":"Essence 215"},{"CanFly":true,"Id":216,"Name":"Essence 216"},{"CanFly":false,"Id":217,"Name":"Essence 217"},{"CanFly":true,"Id":218,"Name":"Essence 218"},{"CanFly":false,"Id":219,"Name":"Essence 219"},{"CanFly":true,"Id":220,"Name":"Essence 220"},{"CanFly":false,"Id":221,"Name":"Essence 221"},{"CanFly":true,"Id":222,"Name":"Essence 222"},{"CanFly":false,"Id":223,"Name":"Essence 223"},{"CanFly":true,"Id":224,"Name":"Essence 224"},{"CanFly":false,"Id":225,"Name":"Essence 225"},{"CanFly":true,"Id":226,"Name":"Essence 226"},{"CanFly":false,"Id":227,"Name":"Essence 227"},{"CanFly":true,"Id":228,"Name":"Essence 228"},{"CanFly":false,"Id":229,"Name":"Essence 229"},{"CanFly":true,"Id":230,"Name":"Essence 230"},{"CanFly":false,"Id":231,"Name":"Essence 231"},{"CanFly":true,"Id":232,"Name":"Essence 232"},{"CanFly":false,"Id":233,"Name":"Essence 233"},{"CanFly":true,"Id":234,"Name":"Essence 234"},{"CanFly":false,"Id":235,"Name":"Essence 235"},{"CanFly":true,"Id":236,"Name":"Essence 236"},{"CanFly":false,"Id":237,"Name":"Essence 237"},{"CanFly":true,"Id":238,"Name":"Essence 238"},{"CanFly":false,"Id":239,"Name":"Essence 239"},{"CanFly":true,"Id":240,"Name":"Essence 240"},{"CanFly":false,"Id":241,"Name":"Essence 241"},{"CanFly":true,"Id":242,"Name":"Essence 242"},{"CanFly":false,"Id":243,"Name":"Essence 243"},{"CanFly":true,"Id":244,"Name":"Essence 244"},{"CanFly":false,"Id":245,"Name":"Essence 245"},{"CanFly":true,"Id":246,"Name":"Essence 246"},{"CanFly":false,"Id":247,"Name":"Essence 247"},{"CanFly":true,"Id":248,"Name":"Essence 248"},{"CanFly":false,"Id":249,"Name":"Essence 249"},{"CanFly":true,"Id":250,"Name":"Essence 250"},{"CanFly":false,"Id":251,"Name":"Essence 251"},{"CanFly":true,"Id":252,"Name":"Essence 252"},{"CanFly":false,"Id":253,"Name":"Essence 253"},{"CanFly":true,"Id":254,"Name":"Essence 254"},{"CanFly":false,"Id":255,"Name":"Essence 255"},{"CanFly":true,"Id":256,"Name":"Essence 256"},{"CanFly":false,"Id":257,"Name":"Essence 257"},{"CanFly":true,"Id":258,"Name":"Essence 258"},{"CanFly":false,"Id":259,"Name":"Essence 259"},{"CanFly":true,"Id":260,"Name":"Essence 260"},{"CanFly":false,"Id":261,"Name":"Essence 261"},{"CanFly":true,"Id":262,"Name":"Essence 262"},{"CanFly":false,"Id":263,"Name":"Essence 263"},{"CanFly":true,"Id":264,"Name":"Essence 264"},{"CanFly":false,"Id":265,"Name":"Essence 265"},{"CanFly":true,"Id":266,"Name":"Essence 266"},{"CanFly":false,"Id":267,"Name":"Essence 267"},{"CanFly":true,"Id":268,"Name":"Essence 268"},{"CanFly":false,"Id":269,"Name":"Essence 269"},{"CanFly":true,"Id":270,"Name":"Essence 270"},{"CanFly":false,"Id":271,"Name":"Essence 271"},{"CanFly":true,"Id":272,"Name":"Essence 272"},{"CanFly":false,"Id":273,"Name":"Essence 273"},{"CanFly":true,"Id":274,"Name":"Essence 274"},{"CanFly":false,"Id":275,"Name":"Essence 275"},{"CanFly":true,"Id":276,"Name":"Essence 276"},{"CanFly":false,"Id":277,"Name":"Essence 277"},{"CanFly":true,"Id":278,"Name":"Essence 278"},{"CanFly":false,"Id":279,"Name":"Essence 279"},{"CanFly":true,"Id":280,"Name":"Essence 280"},{"CanFly":false,"Id":281,"Name":"Essence 281"},{"CanFly":true,"Id":282,"Name":"Essence 282"},{"CanFly":false,"Id":283,"Name":"Essence 283"},{"CanFly":true,"Id":284,"Name":"Essence 284"},{"CanFly":false,"Id":285,"Name":"Essence 285"},{"CanFly":true,"Id":286,"Name":"Essence 286"},{"CanFly":false,"Id":287,"Name":"Essence 287"},{"CanFly":true,"Id":288,"Name":"Essence 288"},{"CanFly":false,"Id":289,"Name":"Essence 289"},{"CanFly":true,"Id":290,"Name":"Essence 290"},{"CanFly":false,"Id":291,"Name":"Essence 291"},{"CanFly":true,"Id":292,"Name":"Essence 292"},{"CanFly":false,"Id":293,"Name":"Essence 293"},{"CanFly":true,"Id":294,"Name":"Essence 294"},{"CanFly":false,"Id":295,"Name":"Essence 295"},{"CanFly":true,"Id":296,"Name":"Essence 296"},{"CanFly":false,"Id":297,"Name":"Essence 297"},{"CanFly":true,"Id":298,"Name":"Essence 298"},{"CanFly":false,"Id":299,"Name":"Essence 299"},{"CanFly":true,"Id":300,"Name":"Essence 300"},{"CanFly":false,"Id":301,"Name":"Essence 301"},{"CanFly":true,"Id":302,"Name":"Essence 302"},{"CanFly":false,"Id":303,"Name":"Essence 303"},{"CanFly":true,"Id":304,"Name":"Essence 304"},{"CanFly":false,"Id":305,"Name":"Essence 305"},{"CanFly":true,"Id":306,"Name":"Essence 306"},{"CanFly":false,"Id":307,"Name":"Essence 307"},{"CanFly":true,"Id":308,"Name":"Essence 308"},{"CanFly":false,"Id":309,"Name":"Essence 309"},{"CanFly":true,"Id":310,"Name":"Essence 310"},{"CanFly":false,"Id":311,"Name":"Essence 311"},{"CanFly":true,"Id":312,"Name":"Essence 312"},{"CanFly":false,"Id":313,"Name":"Essence 313"},{"CanFly":true,"Id":314,"Name":"Essence 314"},{"CanFly":false,"Id":315,"Name":"Essence 315"},{"CanFly":true,"Id":316,"Name":"Essence 316"},{"CanFly":false,"Id":317,"Name":"Essence 317"},{"CanFly":true,"Id":318,"Name":"Essence 318"},{"CanFly":false,"Id":319,"Name":"Essence 319"},{"CanFly":true,"Id":320,"Name":"Essence 320"},{"CanFly":false,"Id":321,"Name":"Essence 321"},{"CanFly":true,"Id":322,"Name":"Essence 322"},{"CanFly":false,"Id":323,"Name":"Essence 323"},{"CanFly":true,"Id":324,"Name":"Essence 324"},{"CanFly":false,"Id":325,"Name":"Essence 325"},{"CanFly":true,"Id":326,"Name":"Essence 326"},{"CanFly":false,"Id":327,"Name":"Essence 327"},{"CanFly":true,"Id":328,"Name":"Essence 328"},{"CanFly":false,"Id":329,"Name":"Essence 329"},{"CanFly":true,"Id":330,"Name":"Essence 330"},{"CanFly":false,"Id":331,"Name":"Essence 331"},{"CanFly":true,"Id":332,"Name":"Essence 332"},{"CanFly":false,"Id":333,"Name":"Essence 333"},{"CanFly":true,"Id":334,"Name":"Essence 334"},{"CanFly":false,"Id":335,"Name":"Essence 335"},{"CanFly":true,"Id":336,"Name":"Essence 336"},{"CanFly":false,"Id":337,"Name":"Essence 337"},{"CanFly":true,"Id":338,"Name":"Essence 338"},{"CanFly":false,"Id":339,"Name":"Essence 339"},{"CanFly":true,"Id":340,"Name":"Essence 340"},{"CanFly":false,"Id":341,"Name":"Essence 341"},{"CanFly":true,"Id":342,"Name":"Essence 342"},{"CanFly":false,"Id":343,"Name":"Essence 343"},{"CanFly":true,"Id":344,"Name":"Essence 344"},{"CanFly":false,"Id":345,"Name":"Essence 345"},{"CanFly":true,"Id":346,"Name":"Essence 346"},{"CanFly":false,"Id":347,"Name":"Essence 347"},{"CanFly":true,"Id":348,"Name":"Essence 348"},{"CanFly":false,"Id":349,"Name":"Essence 349"},{"CanFly":true,"Id":350,"Name":"Essence 350"},{"CanFly":false,"Id":351,"Name":"Essence 351"},{"CanFly":true,"Id":352,"Name":"Essence 352"},{"CanFly":false,"Id":353,"Name":"Essence 353"},{"CanFly":true,"Id":354,"Name":"Essence 354"},{"CanFly":false,"Id":355,"Name":"Essence 355"},{"CanFly":true,"Id":356,"Name":"Essence 356"},{"CanFly":false,"Id":357,"Name":"Essence 357"},{"CanFly":true,"Id":358,"Name":"Essence 358"},{"CanFly":false,"Id":359,"Name":"Essence 359"},{"CanFly":true,"Id":360,"Name":"Essence 360"},{"CanFly":false,"Id":361,"Name":"Essence 361"},{"CanFly":true,"Id":362,"Name":"Essence 362"},{"CanFly":false,"Id":363,"Name":"Essence 363"},{"CanFly":true,"Id":364,"Name":"Essence 364"},{"CanFly":false,"Id":365,"Name":"Essence 365"},{"CanFly":true,"Id":366,"Name":"Essence 366"},{"CanFly":false,"Id":367,"Name":"Essence 367"},{"CanFly":true,"Id":368,"Name":"Essence 368"},{"CanFly":false,"Id":369,"Name":"Essence 369"},{"CanFly":true,"Id":370,"Name":"Essence 370"},{"CanFly":false,"Id":371,"Name":"Essence 371"},{"CanFly":true,"Id":372,"Name":"Essence 372"},{"CanFly":false,"Id":373,"Name":"Essence 373"},{"CanFly":true,"Id":374,"Name":"Essence 374"},{"CanFly":false,"Id":375,"Name":"Essence 375"},{"CanFly":true,"Id":376,"Name":"Essence 376"},{"CanFly":false,"Id":377,"Name":"Essence 377"},{"CanFly":true,"Id":378,"Name":"Essence 378"},{"CanFly":false,"Id":379,"Name":"Essence 379"},{"CanFly":true,"Id":380,"Name":"Essence 380"},{"CanFly":false,"Id":381,"Name":"Essence 381"},{"CanFly":true,"Id":382,"Name":"Essence 382"},{"CanFly":false,"Id":383,"Name":"Essence 383"},{"CanFly":true,"Id":384,"Name":"Essence 384"},{"CanFly":false,"Id":385,"Name":"Essence 385"},{"CanFly":true,"Id":386,"Name":"Essence 386"},{"CanFly":false,"Id":387,"Name":"Essence 387"},{"CanFly":true,"Id":388,"Name":"Essence 388"},{"CanFly":false,"Id":389,"Name":"Essence 389"},{"CanFly":true,"Id":390,"Name":"Essence 390"},{"CanFly":false,"Id":391,"Name":"Essence 391"},{"CanFly":true,"Id":392,"Name":"Essence 392"},{"CanFly":false,"Id":393,"Name":"Essence 393"},{"CanFly":true,"Id":394,"Name":"Essence 394"},{"CanFly":false,"Id":395,"Name":"Essence 395"},{"CanFly":true,"Id":396,"Name":"Essence 396"},{"CanFly":false,"Id":397,"Name":"Essence 397"},{"CanFly":true,"Id":398,"Name":"Essence 398"},{"CanFly":false,"Id":399,"Name":"Essence 399"},{"CanFly":true,"Id":400,"Name":"Essence 400"},{"CanFly":false,"Id":401,"Name":"Essence 401"},{"CanFly":true,"Id":402,"Name":"Essence 402"},{"CanFly":false,"Id":403,"Name":"Essence 403"},{"CanFly":true,"Id":404,"Name":"Essence 404"},{"CanFly":false,"Id":405,"Name":"Essence 405"},{"CanFly":true,"Id":406,"Name":"Essence 406"},{"CanFly":false,"Id":407,"Name":"Essence 407"},{"CanFly":true,"Id":408,"Name":"Essence 408"},{"CanFly":false,"Id":409,"Name":"Essence 409"},{"CanFly":true,"Id":410,"Name":"Essence 410"},{"CanFly":false,"Id":411,"Name":"Essence 411"},{"CanFly":true,"Id":412,"Name":"Essence 412"},{"CanFly":false,"Id":413,"Name":"Essence 413"},{"CanFly":true,"Id":414,"Name":"Essence 414"},{"CanFly":false,"Id":415,"Name":"Essence 415"},{"CanFly":true,"Id":416,"Name":"Essence 416"},{"CanFly":false,"Id":417,"Name":"Essence 417"},{"CanFly":true,"Id":418,"Name":"Essence 418"},{"CanFly":false,"Id":419,"Name":"Essence 419"},{"CanFly":true,"Id":420,"Name":"Essence 420"},{"CanFly":false,"Id":421,"Name":"Essence 421"},{"CanFly":true,"Id":422,"Name":"Essence 422"},{"CanFly":false,"Id":423,"Name":"Essence 423"},{"CanFly":true,"Id":424,"Name":"Essence 424"},{"CanFly":false,"Id":425,"Name":"Essence 425"},{"CanFly":true,"Id":426,"Name":"Essence 426"},{"CanFly":false,"Id":427,"Name":"Essence 427"},{"CanFly":true,"Id":428,"Name":"Essence 428"},{"CanFly":false,"Id":429,"Name":"Essence 429"},{"CanFly":true,"Id":430,"Name":"Essence 430"},{"CanFly":false,"Id":431,"Name":"Essence 431"},{"CanFly":true,"Id":432,"Name":"Essence 432"},{"CanFly":false,"Id":433,"Name":"Essence 433"},{"CanFly":true,"Id":434,"Name":"Essence 434"},{"CanFly":false,"Id":435,"Name":"Essence 435"},{"CanFly":true,"Id":436,"Name":"Essence 436"},{"CanFly":false,"Id":437,"Name":"Essence 437"},{"CanFly":true,"Id":438,"Name":"Essence 438"},{"CanFly":false,"Id":439,"Name":"Essence 439"},{"CanFly":true,"Id":440,"Name":"Essence 440"},{"CanFly":false,"Id":441,"Name":"Essence 441"},{"CanFly":true,"Id":442,"Name":"Essence 442"},{"CanFly":false,"Id":443,"Name":"Essence 443"},{"CanFly":true,"Id":444,"Name":"Essence 444"},{"CanFly":false,"Id":445,"Name":"Essence 445"},{"CanFly":true,"Id":446,"Name":"Essence 446"},{"CanFly":false,"Id":447,"Name":"Essence 447"},{"CanFly":true,"Id":448,"Name":"Essence 448"},{"CanFly":false,"Id":449,"Name":"Essence 449"},{"CanFly":true,"Id":450,"Name":"Essence 450"},{"CanFly":false,"Id":451,"Name":"Essence 451"},{"CanFly":true,"Id":452,"Name":"Essence 452"},{"CanFly":false,"Id":453,"Name":"Essence 453"},{"CanFly":true,"Id":454,"Name":"Essence 454"},{"CanFly":false,"Id":455,"Name":"Essence 455"},{"CanFly":true,"Id":456,"Name":"Essence 456"},{"CanFly":false,"Id":457,"Name":"Essence 457"},{"CanFly":true,"Id":458,"Name":"Essence 458"},{"CanFly":false,"Id":459,"Name":"Essence 459"},{"CanFly":true,"Id":460,"Name":"Essence 460"},{"CanFly":false,"Id":461,"Name":"Essence 461"},{"CanFly":true,"Id":462,"Name":"Essence 462"},{"CanFly":false,"Id":463,"Name":"Essence 463"},{"CanFly":true,"Id":464,"Name":"Essence 464"},{"CanFly":false,"Id":465,"Name":"Essence 465"},{"CanFly":true,"Id":466,"Name":"Essence 466"},{"CanFly":false,"Id":467,"Name":"Essence 467"},{"CanFly":true,"Id":468,"Name":"Essence 468"},{"CanFly":false,"Id":469,"Name":"Essence 469"},{"CanFly":true,"Id":470,"Name":"Essence 470"},{"CanFly":false,"Id":471,"Name":"Essence 471"},{"CanFly":true,"Id":472,"Name":"Essence 472"},{"CanFly":false,"Id":473,"Name":"Essence 473"},{"CanFly":true,"Id":474,"Name":"Essence 474"},{"CanFly":false,"Id":475,"Name":"Essence 475"},{"CanFly":true,"Id":476,"Name":"Essence 476"},{"CanFly":false,"Id":477,"Name":"Essence 477"},{"CanFly":true,"Id":478,"Name":"Essence 478"},{"CanFly":false,"Id":479,"Name":"Essence 479"},{"CanFly":true,"Id":480,"Name":"Essence 480"},{"CanFly":false,"Id":481,"Name":"Essence 481"},{"CanFly":true,"Id":482,"Name":"Essence 482"},{"CanFly":false,"Id":483,"Name":"Essence 483"},{"CanFly":true,"Id":484,"Name":"Essence 484"},{"CanFly":false,"Id":485,"Name":"Essence 485"},{"CanFly":true,"Id":486,"Name":"Essence 486"},{"CanFly":false,"Id":487,"Name":"Essence 487"},{"CanFly":true,"Id":488,"Name":"Essence 488"},{"CanFly":false,"Id":489,"Name":"Essence 489"},{"CanFly":true,"Id":490,"Name":"Essence 490"},{"CanFly":false,"Id":491,"Name":"Essence 491"},{"CanFly":true,"Id":492,"Name":"Essence 492"},{"CanFly":false,"Id":493,"Name":"Essence 493"},{"CanFly":true,"Id":494,"Name":"Essence 494"},{"CanFly":false,"Id":495,"Name":"Essence 495"},{"CanFly":true,"Id":496,"Name":"Essence 496"},{"CanFly":false,"Id":497,"Name":"Essence 497"},{"CanFly":true,"Id":498,"Name":"Essence 498"},{"CanFly":false,"Id":499,"Name":"Essence 499"},{"CanFly":true,"Id":500,"Name":"Essence 500"},{"CanFly":false,"Id":501,"Name":"Essence 501"},{"CanFly":true,"Id":502,"Name":"Essence 502"},{"CanFly":false,"Id":503,"Name":"Essence 503"},{"CanFly":true,"Id":504,"Name":"Essence 504"},{"CanFly":false,"Id":505,"Name":"Essence 505"},{"CanFly":true,"Id":506,"Name":"Essence 506"},{"CanFly":false,"Id":507,"Name":"Essence 507"},{"CanFly":true,"Id":508,"Name":"Essence 508"},{"CanFly":false,"Id":509,"Name":"Essence 509"},{"CanFly":true,"Id":510,"Name":"Essence 510"},{"CanFly":false,"Id":511,"Name":"Essence 511"},{"CanFly":true,"Id":512,"Name":"Essence 512"},{"CanFly":false,"Id":513,"Name":"Essence 513"},{"CanFly":true,"Id":514,"Name":"Essence 514"},{"CanFly":false,"Id":515,"Name":"Essence 515"},{"CanFly":true,"Id":516,"Name":"Essence 516"},{"CanFly":false,"Id":517,"Name":"Essence 517"},{"CanFly":true,"Id":518,"Name":"Essence 518"},{"CanFly":false,"Id":519,"Name":"Essence 519"},{"CanFly":true,"Id":520,"Name":"Essence 520"},{"CanFly":false,"Id":521,"Name":"Essence 521"},{"CanFly":true,"Id":522,"Name":"Essence 522"},{"CanFly":false,"Id":523,"Name":"Essence 523"},{"CanFly":true,"Id":524,"Name":"Essence 524"},{"CanFly":false,"Id":525,"Name":"Essence 525"},{"CanFly":true,"Id":526,"Name":"Essence 526"},{"CanFly":false,"Id":527,"Name":"Essence 527"},{"CanFly":true,"Id":528,"Name":"Essence 528"},{"CanFly":false,"Id":529,"Name":"Essence 529"},{"CanFly":true,"Id":530,"Name":"Essence 530"},{"CanFly":false,"Id":531,"Name":"Essence 531"},{"CanFly":true,"Id":532,"Name":"Essence 532"},{"CanFly":false,"Id":533,"Name":"Essence 533"},{"CanFly":true,"Id":534,"Name":"Essence 534"},{"CanFly":false,"Id":535,"Name":"Essence 535"},{"CanFly":true,"Id":536,"Name":"Essence 536"},{"CanFly":false,"Id":537,"Name":"Essence 537"},{"CanFly":true,"Id":538,"Name":"Essence 538"},{"CanFly":false,"Id":539,"Name":"Essence 539"},{"CanFly":true,"Id":540,"Name":"Essence 540"},{"CanFly":false,"Id":541,"Name":"Essence 541"},{"CanFly":true,"Id":542,"Name":"Essence 542"},{"CanFly":false,"Id":543,"Name":"Essence 543"},{"CanFly":true,"Id":544,"Name":"Essence 544"},{"CanFly":false,"Id":545,"Name":"Essence 545"},{"CanFly":true,"Id":546,"Name":"Essence 546"},{"CanFly":false,"Id":547,"Name":"Essence 547"},{"CanFly":true,"Id":548,"Name":"Essence 548"},{"CanFly":false,"Id":549,"Name":"Essence 549"},{"CanFly":true,"Id":550,"Name":"Essence 550"},{"CanFly":false,"Id":551,"Name":"Essence 551"},{"CanFly":true,"Id":552,"Name":"Essence 552"},{"CanFly":false,"Id":553,"Name":"Essence 553"},{"CanFly":true,"Id":554,"Name":"Essence 554"},{"CanFly":false,"Id":555,"Name":"Essence 555"},{"CanFly":true,"Id":556,"Name":"Essence 556"},{"CanFly":false,"Id":557,"Name":"Essence 557"},{"CanFly":true,"Id":558,"Name":"Essence 558"},{"CanFly":false,"Id":559,"Name":"Essence 559"},{"CanFly":true,"Id":560,"Name":"Essence 560"},{"CanFly":false,"Id":561,"Name":"Essence 561"},{"CanFly":true,"Id":562,"Name":"Essence 562"},{"CanFly":false,"Id":563,"Name":"Essence 563"},{"CanFly":true,"Id":564,"Name":"Essence 564"},{"CanFly":false,"Id":565,"Name":"Essence 565"},{"CanFly":true,"Id":566,"Name":"Essence 566"},{"CanFly":false,"Id":567,"Name":"Essence 567"},{"CanFly":true,"Id":568,"Name":"Essence 568"},{"CanFly":false,"Id":569,"Name":"Essence 569"},{"CanFly":true,"Id":570,"Name":"Essence 570"},{"CanFly":false,"Id":571,"Name":"Essence 571"},{"CanFly":true,"Id":572,"Name":"Essence 572"},{"CanFly":false,"Id":573,"Name":"Essence 573"},{"CanFly":true,"Id":574,"Name":"Essence 574"},{"CanFly":false,"Id":575,"Name":"Essence 575"},{"CanFly":true,"Id":576,"Name":"Essence 576"},{"CanFly":false,"Id":577,"Name":"Essence 577"},{"CanFly":true,"Id":578,"Name":"Essence 578"},{"CanFly":false,"Id":579,"Name":"Essence 579"},{"CanFly":true,"Id":580,"Name":"Essence 580"},{"CanFly":false,"Id":581,"Name":"Essence 581"},{"CanFly":true,"Id":582,"Name":"Essence 582"},{"CanFly":false,"Id":583,"Name":"Essence 583"},{"CanFly":true,"Id":584,"Name":"Essence 584"},{"CanFly":false,"Id":585,"Name":"Essence 585"},{"CanFly":true,"Id":586,"Name":"Essence 586"},{"CanFly":false,"Id":587,"Name":"Essence 587"},{"CanFly":true,"Id":588,"Name":"Essence 588"},{"CanFly":false,"Id":589,"Name":"Essence 589"},{"CanFly":true,"Id":590,"Name":"Essence 590"},{"CanFly":false,"Id":591,"Name":"Essence 591"},{"CanFly":true,"Id":592,"Name":"Essence 592"},{"CanFly":false,"Id":593,"Name":"Essence 593"},{"CanFly":true,"Id":594,"Name":"Essence 594"},{"CanFly":false,"Id":595,"Name":"Essence 595"},{"CanFly":true,"Id":596,"Name":"Essence 596"},{"CanFly":false,"Id":597,"Name":"Essence 597"},{"CanFly":true,"Id":598,"Name":"Essence 598"},{"CanFly":false,"Id":599,"Name":"Essence 599"},{"CanFly":true,"Id":600,"Name":"Essence 600"},{"CanFly":false,"Id":601,"Name":"Essence 601"},{"CanFly":true,"Id":602,"Name":"Essence 602"},{"CanFly":false,"Id":603,"Name":"Essence 603"},{"CanFly":true,"Id":604,"Name":"Essence 604"},{"CanFly":false,"Id":605,"Name":"Essence 605"},{"CanFly":true,"Id":606,"Name":"Essence 606"},{"CanFly":false,"Id":607,"Name":"Essence 607"},{"CanFly":true,"Id":608,"Name":"Essence 608"},{"CanFly":false,"Id":609,"Name":"Essence 609"},{"CanFly":true,"Id":610,"Name":"Essence 610"},{"CanFly":false,"Id":611,"Name":"Essence 611"},{"CanFly":true,"Id":612,"Name":"Essence 612"},{"CanFly":false,"Id":613,"Name":"Essence 613"},{"CanFly":true,"Id":614,"Name":"Essence 614"},{"CanFly":false,"Id":615,"Name":"Essence 615"},{"CanFly":true,"Id":616,"Name":"Essence 616"},{"CanFly":false,"Id":617,"Name":"Essence 617"},{"CanFly":true,"Id":618,"Name":"Essence 618"},{"CanFly":false,"Id":619,"Name":"Essence 619"},{"CanFly":true,"Id":620,"Name":"Essence 620"},{"CanFly":false,"Id":621,"Name":"Essence 621"},{"CanFly":true,"Id":622,"Name":"Essence 622"},{"CanFly":false,"Id":623,"Name":"Essence 623"},{"CanFly":true,"Id":624,"Name":"Essence 624"},{"CanFly":false,"Id":625,"Name":"Essence 625"},{"CanFly":true,"Id":626,"Name":"Essence 626"},{"CanFly":false,"Id":627,"Name":"Essence 627"},{"CanFly":true,"Id":628,"Name":"Essence 628"},{"CanFly":false,"Id":629,"Name":"Essence 629"},{"CanFly":true,"Id":630,"Name":"Essence 630"},{"CanFly":false,"Id":631,"Name":"Essence 631"},{"CanFly":true,"Id":632,"Name":"Essence 632"},{"CanFly":false,"Id":633,"Name":"Essence 633"},{"CanFly":true,"Id":634,"Name":"Essence 634"},{"CanFly":false,"Id":635,"Name":"Essence 635"},{"CanFly":true,"Id":636,"Name":"Essence 636"},{"CanFly":false,"Id":637,"Name":"Essence 637"},{"CanFly":true,"Id":638,"Name":"Essence 638"},{"CanFly":false,"Id":639,"Name":"Essence 639"},{"CanFly":true,"Id":640,"Name":"Essence 640"},{"CanFly":false,"Id":641,"Name":"Essence 641"},{"CanFly":true,"Id":642,"Name":"Essence 642"},{"CanFly":false,"Id":643,"Name":"Essence 643"},{"CanFly":true,"Id":644,"Name":"Essence 644"},{"CanFly":false,"Id":645,"Name":"Essence 645"},{"CanFly":true,"Id":646,"Name":"Essence 646"},{"CanFly":false,"Id":647,"Name":"Essence 647"},{"CanFly":true,"Id":648,"Name":"Essence 648"},{"CanFly":false,"Id":649,"Name":"Essence 649"},{"CanFly":true,"Id":650,"Name":"Essence 650"},{"CanFly":false,"Id":651,"Name":"Essence 651"},{"CanFly":true,"Id":652,"Name":"Essence 652"},{"CanFly":false,"Id":653,"Name":"Essence 653"},{"CanFly":true,"Id":654,"Name":"Essence 654"},{"CanFly":false,"Id":655,"Name":"Essence 655"},{"CanFly":true,"Id":656,"Name":"Essence 656"},{"CanFly":false,"Id":657,"Name":"Essence 657"},{"CanFly":true,"Id":658,"Name":"Essence 658"},{"CanFly":false,"Id":659,"Name":"Essence 659"},{"CanFly":true,"Id":660,"Name":"Essence 660"},{"CanFly":false,"Id":661,"Name":"Essence 661"},{"CanFly":true,"Id":662,"Name":"Essence 662"},{"CanFly":false,"Id":663,"Name":"Essence 663"},{"CanFly":true,"Id":664,"Name":"Essence 664"},{"CanFly":false,"Id":665,"Name":"Essence 665"},{"CanFly":true,"Id":666,"Name":"Essence 666"},{"CanFly":false,"Id":667,"Name":"Essence 667"},{"CanFly":true,"Id":668,"Name":"Essence 668"},{"CanFly":false,"Id":669,"Name":"Essence 669"},{"CanFly":true,"Id":670,"Name":"Essence 670"},{"CanFly":false,"Id":671,"Name":"Essence 671"},{"CanFly":true,"Id":672,"Name":"Essence 672"},{"CanFly":false,"Id":673,"Name":"Essence 673"},{"CanFly":true,"Id":674,"Name":"Essence 674"},{"CanFly":false,"Id":675,"Name":"Essence 675"},{"CanFly":true,"Id":676,"Name":"Essence 676"},{"CanFly":false,"Id":677,"Name":"Essence 677"},{"CanFly":true,"Id":678,"Name":"Essence 678"},{"CanFly":false,"Id":679,"Name":"Essence 679"},{"CanFly":true,"Id":680,"Name":"Essence 680"},{"CanFly":false,"Id":681,"Name":"Essence 681"},{"CanFly":true,"Id":682,"Name":"Essence 682"},{"CanFly":false,"Id":683,"Name":"Essence 683"},{"CanFly":true,"Id":684,"Name":"Essence 684"},{"CanFly":false,"Id":685,"Name":"Essence 685"},{"CanFly":true,"Id":686,"Name":"Essence 686"},{"CanFly":false,"Id":687,"Name":"Essence 687"},{"CanFly":true,"Id":688,"Name":"Essence 688"},{"CanFly":false,"Id":689,"Name":"Essence 689"},{"CanFly":true,"Id":690,"Name":"Essence 690"},{"CanFly":false,"Id":691,"Name":"Essence 691"},{"CanFly":true,"Id":692,"Name":"Essence 692"},{"CanFly":false,"Id":693,"Name":"Essence 693"},{"CanFly":true,"Id":694,"Name":"Essence 694"},{"CanFly":false,"Id":695,"Name":"Essence 695"},{"CanFly":true,"Id":696,"Name":"Essence 696"},{"CanFly":false,"Id":697,"Name":"Essence 697"},{"CanFly":true,"Id":698,"Name":"Essence 698"},{"CanFly":false,"Id":699,"Name":"Essence 699"},{"CanFly":true,"Id":700,"Name":"Essence 700"},{"CanFly":false,"Id":701,"Name":"Essence 701"},{"CanFly":true,"Id":702,"Name":"Essence 702"},{"CanFly":false,"Id":703,"Name":"Essence 703"},{"CanFly":true,"Id":704,"Name":"Essence 704"},{"CanFly":false,"Id":705,"Name":"Essence 705"},{"CanFly":true,"Id":706,"Name":"Essence 706"},{"CanFly":false,"Id":707,"Name":"Essence 707"},{"CanFly":true,"Id":708,"Name":"Essence 708"},{"CanFly":false,"Id":709,"Name":"Essence 709"},{"CanFly":true,"Id":710,"Name":"Essence 710"},{"CanFly":false,"Id":711,"Name":"Essence 711"},{"CanFly":true,"Id":712,"Name":"Essence 712"},{"CanFly":false,"Id":713,"Name":"Essence 713"},{"CanFly":true,"Id":714,"Name":"Essence 714"},{"CanFly":false,"Id":715,"Name":"Essence 715"},{"CanFly":true,"Id":716,"Name":"Essence 716"},{"CanFly":false,"Id":717,"Name":"Essence 717"},{"CanFly":true,"Id":718,"Name":"Essence 718"},{"CanFly":false,"Id":719,"Name":"Essence 719"},{"CanFly":true,"Id":720,"Name":"Essence 720"},{"CanFly":false,"Id":721,"Name":"Essence 721"},{"CanFly":true,"Id":722,"Name":"Essence 722"},{"CanFly":false,"Id":723,"Name":"Essence 723"},{"CanFly":true,"Id":724,"Name":"Essence 724"},{"CanFly":false,"Id":725,"Name":"Essence 725"},{"CanFly":true,"Id":726,"Name":"Essence 726"},{"CanFly":false,"Id":727,"Name":"Essence 727"},{"CanFly":true,"Id":728,"Name":"Essence 728"},{"CanFly":false,"Id":729,"Name":"Essence 729"},{"CanFly":true,"Id":730,"Name":"Essence 730"},{"CanFly":false,"Id":731,"Name":"Essence 731"},{"CanFly":true,"Id":732,"Name":"Essence 732"},{"CanFly":false,"Id":733,"Name":"Essence 733"},{"CanFly":true,"Id":734,"Name":"Essence 734"},{"CanFly":false,"Id":735,"Name":"Essence 735"},{"CanFly":true,"Id":736,"Name":"Essence 736"},{"CanFly":false,"Id":737,"Name":"Essence 737"},{"CanFly":true,"Id":738,"Name":"Essence 738"},{"CanFly":false,"Id":739,"Name":"Essence 739"},{"CanFly":true,"Id":740,"Name":"Essence 740"},{"CanFly":false,"Id":741,"Name":"Essence 741"},{"CanFly":true,"Id":742,"Name":"Essence 742"},{"CanFly":false,"Id":743,"Name":"Essence 743"},{"CanFly":true,"Id":744,"Name":"Essence 744"},{"CanFly":false,"Id":745,"Name":"Essence 745"},{"CanFly":true,"Id":746,"Name":"Essence 746"},{"CanFly":false,"Id":747,"Name":"Essence 747"},{"CanFly":true,"Id":748,"Name":"Essence 748"},{"CanFly":false,"Id":749,"Name":"Essence 749"},{"CanFly":true,"Id":750,"Name":"Essence 750"},{"CanFly":false,"Id":751,"Name":"Essence 751"},{"CanFly":true,"Id":752,"Name":"Essence 752"},{"CanFly":false,"Id":753,"Name":"Essence 753"},{"CanFly":true,"Id":754,"Name":"Essence 754"},{"CanFly":false,"Id":755,"Name":"Essence 755"},{"CanFly":true,"Id":756,"Name":"Essence 756"},{"CanFly":false,"Id":757,"Name":"Essence 757"},{"CanFly":true,"Id":758,"Name":"Essence 758"},{"CanFly":false,"Id":759,"Name":"Essence 759"},{"CanFly":true,"Id":760,"Name":"Essence 760"},{"CanFly":false,"Id":761,"Name":"Essence 761"},{"CanFly":true,"Id":762,"Name":"Essence 762"},{"CanFly":false,"Id":763,"Name":"Essence 763"},{"CanFly":true,"Id":764,"Name":"Essence 764"},{"CanFly":false,"Id":765,"Name":"Essence 765"},{"CanFly":true,"Id":766,"Name":"Essence 766"},{"CanFly":false,"Id":767,"Name":"Essence 767"},{"CanFly":true,"Id":768,"Name":"Essence 768"},{"CanFly":false,"Id":769,"Name":"Essence 769"},{"CanFly":true,"Id":770,"Name":"Essence 770"},{"CanFly":false,"Id":771,"Name":"Essence 771"},{"CanFly":true,"Id":772,"Name":"Essence 772"},{"CanFly":false,"Id":773,"Name":"Essence 773"},{"CanFly":true,"Id":774,"Name":"Essence 774"},{"CanFly":false,"Id":775,"Name":"Essence 775"},{"CanFly":true,"Id":776,"Name":"Essence 776"},{"CanFly":false,"Id":777,"Name":"Essence 777"},{"CanFly":true,"Id":778,"Name":"Essence 778"},{"CanFly":false,"Id":779,"Name":"Essence 779"},{"CanFly":true,"Id":780,"Name":"Essence 780"},{"CanFly":false,"Id":781,"Name":"Essence 781"},{"CanFly":true,"Id":782,"Name":"Essence 782"},{"CanFly":false,"Id":783,"Name":"Essence 783"},{"CanFly":true,"Id":784,"Name":"Essence 784"},{"CanFly":false,"Id":785,"Name":"Essence 785"},{"CanFly":true,"Id":786,"Name":"Essence 786"},{"CanFly":false,"Id":787,"Name":"Essence 787"},{"CanFly":true,"Id":788,"Name":"Essence 788"},{"CanFly":false,"Id":789,"Name":"Essence 789"},{"CanFly":true,"Id":790,"Name":"Essence 790"},{"CanFly":false,"Id":791,"Name":"Essence 791"},{"CanFly":true,"Id":792,"Name":"Essence 792"},{"CanFly":false,"Id":793,"Name":"Essence 793"},{"CanFly":true,"Id":794,"Name":"Essence 794"},{"CanFly":false,"Id":795,"Name":"Essence 795"},{"CanFly":true,"Id":796,"Name":"Essence 796"},{"CanFly":false,"Id":797,"Name":"Essence 797"},{"CanFly":true,"Id":798,"Name":"Essence 798"},{"CanFly":false,"Id":799,"Name":"Essence 799"},{"CanFly":true,"Id":800,"Name":"Essence 800"},{"CanFly":false,"Id":801,"Name":"Essence 801"},{"CanFly":true,"Id":802,"Name":"Essence 802"},{"CanFly":false,"Id":803,"Name":"Essence 803"},{"CanFly":true,"Id":804,"Name":"Essence 804"},{"CanFly":false,"Id":805,"Name":"Essence 805"},{"CanFly":true,"Id":806,"Name":"Essence 806"},{"CanFly":false,"Id":807,"Name":"Essence 807"},{"CanFly":true,"Id":808,"Name":"Essence 808"},{"CanFly":false,"Id":809,"Name":"Essence 809"},{"CanFly":true,"Id":810,"Name":"Essence 810"},{"CanFly":false,"Id":811,"Name":"Essence 811"},{"CanFly":true,"Id":812,"Name":"Essence 812"},{"CanFly":false,"Id":813,"Name":"Essence 813"},{"CanFly":true,"Id":814,"Name":"Essence 814"},{"CanFly":false,"Id":815,"Name":"Essence 815"},{"CanFly":true,"Id":816,"Name":"Essence 816"},{"CanFly":false,"Id":817,"Name":"Essence 817"},{"CanFly":true,"Id":818,"Name":"Essence 818"},{"CanFly":false,"Id":819,"Name":"Essence 819"},{"CanFly":true,"Id":820,"Name":"Essence 820"},{"CanFly":false,"Id":821,"Name":"Essence 821"},{"CanFly":true,"Id":822,"Name":"Essence 822"},{"CanFly":false,"Id":823,"Name":"Essence 823"},{"CanFly":true,"Id":824,"Name":"Essence 824"},{"CanFly":false,"Id":825,"Name":"Essence 825"},{"CanFly":true,"Id":826,"Name":"Essence 826"},{"CanFly":false,"Id":827,"Name":"Essence 827"},{"CanFly":true,"Id":828,"Name":"Essence 828"},{"CanFly":false,"Id":829,"Name":"Essence 829"},{"CanFly":true,"Id":830,"Name":"Essence 830"},{"CanFly":false,"Id":831,"Name":"Essence 831"},{"CanFly":true,"Id":832,"Name":"Essence 832"},{"CanFly":false,"Id":833,"Name":"Essence 833"},{"CanFly":true,"Id":834,"Name":"Essence 834"},{"CanFly":false,"Id":835,"Name":"Essence 835"},{"CanFly":true,"Id":836,"Name":"Essence 836"},{"CanFly":false,"Id":837,"Name":"Essence 837"},{"CanFly":true,"Id":838,"Name":"Essence 838"},{"CanFly":false,"Id":839,"Name":"Essence 839"},{"CanFly":true,"Id":840,"Name":"Essence 840"},{"CanFly":false,"Id":841,"Name":"Essence 841"},{"CanFly":true,"Id":842,"Name":"Essence 842"},{"CanFly":false,"Id":843,"Name":"Essence 843"},{"CanFly":true,"Id":844,"Name":"Essence 844"},{"CanFly":false,"Id":845,"Name":"Essence 845"},{"CanFly":true,"Id":846,"Name":"Essence 846"},{"CanFly":false,"Id":847,"Name":"Essence 847"},{"CanFly":true,"Id":848,"Name":"Essence 848"},{"CanFly":false,"Id":849,"Name":"Essence 849"},{"CanFly":true,"Id":850,"Name":"Essence 850"},{"CanFly":false,"Id":851,"Name":"Essence 851"},{"CanFly":true,"Id":852,"Name":"Essence 852"},{"CanFly":false,"Id":853,"Name":"Essence 853"},{"CanFly":true,"Id":854,"Name":"Essence 854"},{"CanFly":false,"Id":855,"Name":"Essence 855"},{"CanFly":true,"Id":856,"Name":"Essence 856"},{"CanFly":false,"Id":857,"Name":"Essence 857"},{"CanFly":true,"Id":858,"Name":"Essence 858"},{"CanFly":false,"Id":859,"Name":"Essence 859"},{"CanFly":true,"Id":860,"Name":"Essence 860"},{"CanFly":false,"Id":861,"Name":"Essence 861"},{"CanFly":true,"Id":862,"Name":"Essence 862"},{"CanFly":false,"Id":863,"Name":"Essence 863"},{"CanFly":true,"Id":864,"Name":"Essence 864"},{"CanFly":false,"Id":865,"Name":"Essence 865"},{"CanFly":true,"Id":866,"Name":"Essence 866"},{"CanFly":false,"Id":867,"Name":"Essence 867"},{"CanFly":true,"Id":868,"Name":"Essence 868"},{"CanFly":false,"Id":869,"Name":"Essence 869"},{"CanFly":true,"Id":870,"Name":"Essence 870"},{"CanFly":false,"Id":871,"Name":"Essence 871"},{"CanFly":true,"Id":872,"Name":"Essence 872"},{"CanFly":false,"Id":873,"Name":"Essence 873"},{"CanFly":true,"Id":874,"Name":"Essence 874"},{"CanFly":false,"Id":875,"Name":"Essence 875"},{"CanFly":true,"Id":876,"Name":"Essence 876"},{"CanFly":false,"Id":877,"Name":"Essence 877"},{"CanFly":true,"Id":878,"Name":"Essence 878"},{"CanFly":false,"Id":879,"Name":"Essence 879"},{"CanFly":true,"Id":880,"Name":"Essence 880"},{"CanFly":false,"Id":881,"Name":"Essence 881"},{"CanFly":true,"Id":882,"Name":"Essence 882"},{"CanFly":false,"Id":883,"Name":"Essence 883"},{"CanFly":true,"Id":884,"Name":"Essence 884"},{"CanFly":false,"Id":885,"Name":"Essence 885"},{"CanFly":true,"Id":886,"Name":"Essence 886"},{"CanFly":false,"Id":887,"Name":"Essence 887"},{"CanFly":true,"Id":888,"Name":"Essence 888"},{"CanFly":false,"Id":889,"Name":"Essence 889"},{"CanFly":true,"Id":890,"Name":"Essence 890"},{"CanFly":false,"Id":891,"Name":"Essence 891"},{"CanFly":true,"Id":892,"Name":"Essence 892"},{"CanFly":false,"Id":893,"Name":"Essence 893"},{"CanFly":true,"Id":894,"Name":"Essence 894"},{"CanFly":false,"Id":895,"Name":"Essence 895"},{"CanFly":true,"Id":896,"Name":"Essence 896"},{"CanFly":false,"Id":897,"Name":"Essence 897"},{"CanFly":true,"Id":898,"Name":"Essence 898"},{"CanFly":false,"Id":899,"Name":"Essence 899"},{"CanFly":true,"Id":900,"Name":"Essence 900"},{"CanFly":false,"Id":901,"Name":"Essence 901"},{"CanFly":true,"Id":902,"Name":"Essence 902"},{"CanFly":false,"Id":903,"Name":"Essence 903"},{"CanFly":true,"Id":904,"Name":"Essence 904"},{"CanFly":false,"Id":905,"Name":"Essence 905"},{"CanFly":true,"Id":906,"Name":"Essence 906"},{"CanFly":false,"Id":907,"Name":"Essence 907"},{"CanFly":true,"Id":908,"Name":"Essence 908"},{"CanFly":false,"Id":909,"Name":"Essence 909"},{"CanFly":true,"Id":910,"Name":"Essence 910"},{"CanFly":false,"Id":911,"Name":"Essence 911"},{"CanFly":true,"Id":912,"Name":"Essence 912"},{"CanFly":false,"Id":913,"Name":"Essence 913"},{"CanFly":true,"Id":914,"Name":"Essence 914"},{"CanFly":false,"Id":915,"Name":"Essence 915"},{"CanFly":true,"Id":916,"Name":"Essence 916"},{"CanFly":false,"Id":917,"Name":"Essence 917"},{"CanFly":true,"Id":918,"Name":"Essence 918"},{"CanFly":false,"Id":919,"Name":"Essence 919"},{"CanFly":true,"Id":920,"Name":"Essence 920"},{"CanFly":false,"Id":921,"Name":"Essence 921"},{"CanFly":true,"Id":922,"Name":"Essence 922"},{"CanFly":false,"Id":923,"Name":"Essence 923"},{"CanFly":true,"Id":924,"Name":"Essence 924"},{"CanFly":false,"Id":925,"Name":"Essence 925"},{"CanFly":true,"Id":926,"Name":"Essence 926"},{"CanFly":false,"Id":927,"Name":"Essence 927"},{"CanFly":true,"Id":928,"Name":"Essence 928"},{"CanFly":false,"Id":929,"Name":"Essence 929"},{"CanFly":true,"Id":930,"Name":"Essence 930"},{"CanFly":false,"Id":931,"Name":"Essence 931"},{"CanFly":true,"Id":932,"Name":"Essence 932"},{"CanFly":false,"Id":933,"Name":"Essence 933"},{"CanFly":true,"Id":934,"Name":"Essence 934"},{"CanFly":false,"Id":935,"Name":"Essence 935"},{"CanFly":true,"Id":936,"Name":"Essence 936"},{"CanFly":false,"Id":937,"Name":"Essence 937"},{"CanFly":true,"Id":938,"Name":"Essence 938"},{"CanFly":false,"Id":939,"Name":"Essence 939"},{"CanFly":true,"Id":940,"Name":"Essence 940"},{"CanFly":false,"Id":941,"Name":"Essence 941"},{"CanFly":true,"Id":942,"Name":"Essence 942"},{"CanFly":false,"Id":943,"Name":"Essence 943"},{"CanFly":true,"Id":944,"Name":"Essence 944"},{"CanFly":false,"Id":945,"Name":"Essence 945"},{"CanFly":true,"Id":946,"Name":"Essence 946"},{"CanFly":false,"Id":947,"Name":"Essence 947"},{"CanFly":true,"Id":948,"Name":"Essence 948"},{"CanFly":false,"Id":949,"Name":"Essence 949"},{"CanFly":true,"Id":950,"Name":"Essence 950"},{"CanFly":false,"Id":951,"Name":"Essence 951"},{"CanFly":true,"Id":952,"Name":"Essence 952"},{"CanFly":false,"Id":953,"Name":"Essence 953"},{"CanFly":true,"Id":954,"Name":"Essence 954"},{"CanFly":false,"Id":955,"Name":"Essence 955"},{"CanFly":true,"Id":956,"Name":"Essence 956"},{"CanFly":false,"Id":957,"Name":"Essence 957"},{"CanFly":true,"Id":958,"Name":"Essence 958"},{"CanFly":false,"Id":959,"Name":"Essence 959"},{"CanFly":true,"Id":960,"Name":"Essence 960"},{"CanFly":false,"Id":961,"Name":"Essence 961"},{"CanFly":true,"Id":962,"Name":"Essence 962"},{"CanFly":false,"Id":963,"Name":"Essence 963"},{"CanFly":true,"Id":964,"Name":"Essence 964"},{"CanFly":false,"Id":965,"Name":"Essence 965"},{"CanFly":true,"Id":966,"Name":"Essence 966"},{"CanFly":false,"Id":967,"Name":"Essence 967"},{"CanFly":true,"Id":968,"Name":"Essence 968"},{"CanFly":false,"Id":969,"Name":"Essence 969"},{"CanFly":true,"Id":970,"Name":"Essence 970"},{"CanFly":false,"Id":971,"Name":"Essence 971"},{"CanFly":true,"Id":972,"Name":"Essence 972"},{"CanFly":false,"Id":973,"Name":"Essence 973"},{"CanFly":true,"Id":974,"Name":"Essence 974"},{"CanFly":false,"Id":975,"Name":"Essence 975"},{"CanFly":true,"Id":976,"Name":"Essence 976"},{"CanFly":false,"Id":977,"Name":"Essence 977"},{"CanFly":true,"Id":978,"Name":"Essence 978"},{"CanFly":false,"Id":979,"Name":"Essence 979"},{"CanFly":true,"Id":980,"Name":"Essence 980"},{"CanFly":false,"Id":981,"Name":"Essence 981"},{"CanFly":true,"Id":982,"Name":"Essence 982"},{"CanFly":false,"Id":983,"Name":"Essence 983"},{"CanFly":true,"Id":984,"Name":"Essence 984"},{"CanFly":false,"Id":985,"Name":"Essence 985"},{"CanFly":true,"Id":986,"Name":"Essence 986"},{"CanFly":false,"Id":987,"Name":"Essence 987"},{"CanFly":true,"Id":988,"Name":"Essence 988"},{"CanFly":false,"Id":989,"Name":"Essence 989"},{"CanFly":true,"Id":990,"Name":"Essence 990"},{"CanFly":false,"Id":991,"Name":"Essence 991"},{"CanFly":true,"Id":992,"Name":"Essence 992"},{"CanFly":false,"Id":993,"Name":"Essence 993"},{"CanFly":true,"Id":994,"Name":"Essence 994"},{"CanFly":false,"Id":995,"Name":"Essence 995"},{"CanFly":true,"Id":996,"Name":"Essence 996"},{"CanFly":false,"Id":997,"Name":"Essence 997"},{"CanFly":true,"Id":998,"Name":"Essence 998"},{"CanFly":false,"Id":999,"Name":"Essence 999"}]